LICENSE.txt
MANIFEST.in
README.md
setup.py
mqttk/MQTT_manager.py
mqttk/__init__.py
mqttk/__main__.py
mqttk/config_handler.py
mqttk/constants.py
mqttk/helpers.py
mqttk/hex_printer.py
mqttk/mqtt_fx_config_parser.py
mqttk/mqttk.png
mqttk/mqttk_small.png
mqttk/mqttk_splash.png
mqttk.egg-info/PKG-INFO
mqttk.egg-info/SOURCES.txt
mqttk.egg-info/dependency_links.txt
mqttk.egg-info/entry_points.txt
mqttk.egg-info/requires.txt
mqttk.egg-info/top_level.txt
mqttk/widgets/__init__.py
mqttk/widgets/broker_stats.py
mqttk/widgets/configuration_dialog.py
mqttk/widgets/dialogs.py
mqttk/widgets/header_frame.py
mqttk/widgets/log_tab.py
mqttk/widgets/publish_tab.py
mqttk/widgets/scroll_frame.py
mqttk/widgets/scrolled_text.py
mqttk/widgets/subscribe_tab.py
mqttk/widgets/topic_browser.py