Metadata-Version: 2.1
Name: mqttk
Version: 1.3.1
Summary: A lightweight MQTT client GUI written in pure python
Home-page: https://github.com/matesh/mqttk
Author: Mate Szabo
Author-email: mate@mateszabo.com
Maintainer: Mate Szabo
Maintainer-email: mate@mateszabo.com
License: GPLv3
Download-URL: https://github.com/matesh/mqttk/releases
Platform: UNKNOWN
Requires-Python: >=3.7
